{
  "hash": "7bded92c",
  "configHash": "926de44e",
  "lockfileHash": "19405d04",
  "browserHash": "0b9992d0",
  "optimized": {
    "react": {
      "src": "../../node_modules/react/index.js",
      "file": "react.js",
      "fileHash": "ea02ce1f",
      "needsInterop": true
    },
    "react-dom/client": {
      "src": "../../node_modules/react-dom/client.js",
      "file": "react-dom_client.js",
      "fileHash": "42cfd39f",
      "needsInterop": true
    },
    "react-router-dom": {
      "src": "../../node_modules/react-router-dom/dist/index.js",
      "file": "react-router-dom.js",
      "fileHash": "c9be3055",
      "needsInterop": false
    },
    "axios": {
      "src": "../../node_modules/axios/index.js",
      "file": "axios.js",
      "fileHash": "1fab1293",
      "needsInterop": false
    },
    "framer-motion": {
      "src": "../../node_modules/framer-motion/dist/es/index.mjs",
      "file": "framer-motion.js",
      "fileHash": "6afc6a95",
      "needsInterop": false
    },
    "lucide-react": {
      "src": "../../node_modules/lucide-react/dist/esm/lucide-react.js",
      "file": "lucide-react.js",
      "fileHash": "ef0f3225",
      "needsInterop": false
    },
    "lightweight-charts": {
      "src": "../../node_modules/lightweight-charts/dist/lightweight-charts.development.mjs",
      "file": "lightweight-charts.js",
      "fileHash": "5089a84f",
      "needsInterop": false
    }
  },
  "chunks": {
    "chunk-AU2MKR2E": {
      "file": "chunk-AU2MKR2E.js"
    },
    "chunk-VX2H6PUQ": {
      "file": "chunk-VX2H6PUQ.js"
    },
    "chunk-G3PMV62Z": {
      "file": "chunk-G3PMV62Z.js"
    }
  }
}